{
  "project_info": {
    "project_number": "900646158450",
    "project_id": "mi-learning",
    "storage_bucket": "mi-learning.appspot.com"
  },
  "client": [
    {
      "client_info": {
        "mobilesdk_app_id": "1:900646158450:android:b5b441835987c0b36502eb",
        "android_client_info": {
          "package_name": "com.thinhlh.mi_learning"
        }
      },
      "oauth_client": [
        {
          "client_id": "900646158450-si5cmlr19ca96hqqer25ahjnjhs53j11.apps.googleusercontent.com",
          "client_type": 3
        }
      ],
      "api_key": [
        {
          "current_key": "AIzaSyBGVWOXzjLsdVpdzaHoWecMQ8Og01e4In4"
        }
      ],
      "services": {
        "appinvite_service": {
          "other_platform_oauth_client": [
            {
              "client_id": "900646158450-si5cmlr19ca96hqqer25ahjnjhs53j11.apps.googleusercontent.com",
              "client_type": 3
            },
            {
              "client_id": "900646158450-5slaltjkb88hs3krbigsavr0pth0qim8.apps.googleusercontent.com",
              "client_type": 2,
              "ios_info": {
                "bundle_id": "com.thinhlh.miLearning"
              }
            }
          ]
        }
      }
    }
  ],
  "configuration_version": "1"
}